setup.py
awzozkrbwlsebck/__init__.py
awzozkrbwlsebck/cli.py
awzozkrbwlsebck.egg-info/PKG-INFO
awzozkrbwlsebck.egg-info/SOURCES.txt
awzozkrbwlsebck.egg-info/dependency_links.txt
awzozkrbwlsebck.egg-info/entry_points.txt
awzozkrbwlsebck.egg-info/top_level.txt